README
setup.py
git_calendar/__init__.py
git_calendar/main.py
git_calendar/utils.py
git_calendar.egg-info/PKG-INFO
git_calendar.egg-info/SOURCES.txt
git_calendar.egg-info/dependency_links.txt
git_calendar.egg-info/entry_points.txt
git_calendar.egg-info/requires.txt
git_calendar.egg-info/top_level.txt