Metadata-Version: 1.1
Name: git-calendar
Version: v0.1
Summary: Show a github-like calendar in your git repository.
Home-page: https://github.com/littleq0903/git-calendar
Author: Colin Su
Author-email: littleq0903@gmail.com
License: MIT
Platform: any
Classifier: Development Status :: 5 - Production/Stable
Classifier: Environment :: Console
Classifier: Intended Audience :: Developers
Classifier: License :: OSI Approved :: MIT License
Classifier: Operating System :: OS Independent
Classifier: Programming Language :: Python
Classifier: Topic :: Utilities
Classifier: Topic :: Software Development
